itunes_app_scraper/__init__.py
itunes_app_scraper/http.py
itunes_app_scraper/scraper.py
itunes_app_scraper/util.py
async_itunes_app_scraper_dmi-0.9.5.dist-info/LICENSE
async_itunes_app_scraper_dmi-0.9.5.dist-info/METADATA
async_itunes_app_scraper_dmi-0.9.5.dist-info/WHEEL
async_itunes_app_scraper_dmi-0.9.5.dist-info/top_level.txt
async_itunes_app_scraper_dmi-0.9.5.dist-info/RECORD
