Metadata-Version: 2.1
Name: async-itunes-app-scraper-dmi
Version: 0.9.5
Summary: A lightweight async iTunes App Store scraper based on https://github.com/digitalmethodsinitiative/itunes-app-scraper
Home-page: https://github.com/liorchen/async-itunes-app-scraper
Author: liorchen
Author-email: liorchen2@gmail.com
License: UNKNOWN
Platform: UNKNOWN
Classifier: Programming Language :: Python :: 3
Classifier: License :: OSI Approved :: MIT License
Classifier: Operating System :: OS Independent
Requires-Python: >=3.6
Requires-Dist: aiohttp (<4.0,>=3.5.2)
